sema4ai/crossplatform/__init__.py
sema4ai/crossplatform/_mac.py
sema4ai/crossplatform/_win.py
sema4ai/crossplatform/py.typed
sema4ai_crossplatform-0.1.2.dist-info/LICENSE
sema4ai_crossplatform-0.1.2.dist-info/METADATA
sema4ai_crossplatform-0.1.2.dist-info/WHEEL
sema4ai_crossplatform-0.1.2.dist-info/RECORD
