Metadata-Version: 2.1
Name: sema4ai-crossplatform
Version: 0.1.2
Summary: Sema4.ai crossplatform dependencies
Home-page: https://github.com/Sema4AI/data/
License: Sema4.ai Proprietary (see LICENSE)
Author: Mika H.
Author-email: mika@sema4.ai
Requires-Python: >=3.10,<4.0
Classifier: License :: Other/Proprietary License
Classifier: Programming Language :: Python :: 3
Classifier: Programming Language :: Python :: 3.10
Classifier: Programming Language :: Python :: 3.11
Classifier: Programming Language :: Python :: 3.12
Requires-Dist: comtypes (>=1.4.8,<2.0.0) ; sys_platform == "win32"
Requires-Dist: pywin32 (>=308) ; sys_platform == "win32"
Project-URL: Repository, https://github.com/Sema4AI/data/
